ClojurescriptRumenZhinan/README.md
ClojurescriptRumenZhinan/__init__.py
ClojurescriptRumenZhinan/__main__.py
ClojurescriptRumenZhinan/file.epub
ClojurescriptRumenZhinan/index.html
ClojurescriptRumenZhinan/css/__init__.py
ClojurescriptRumenZhinan/css/annotations.css
ClojurescriptRumenZhinan/css/main.css
ClojurescriptRumenZhinan/css/normalize.css
ClojurescriptRumenZhinan/css/popup.css
ClojurescriptRumenZhinan/font/__init__.py
ClojurescriptRumenZhinan/font/fontello.eot
ClojurescriptRumenZhinan/font/fontello.svg
ClojurescriptRumenZhinan/font/fontello.ttf
ClojurescriptRumenZhinan/font/fontello.woff
ClojurescriptRumenZhinan/img/__init__.py
ClojurescriptRumenZhinan/img/annotator-glyph-sprite.png
ClojurescriptRumenZhinan/img/annotator-icon-sprite.png
ClojurescriptRumenZhinan/img/apple-touch-icon.png
ClojurescriptRumenZhinan/img/cancelfullscreen.png
ClojurescriptRumenZhinan/img/close.png
ClojurescriptRumenZhinan/img/fullscreen.png
ClojurescriptRumenZhinan/img/loader.gif
ClojurescriptRumenZhinan/img/menu-icon.png
ClojurescriptRumenZhinan/img/save.png
ClojurescriptRumenZhinan/img/saved.png
ClojurescriptRumenZhinan/img/settings-s.png
ClojurescriptRumenZhinan/img/settings.png
ClojurescriptRumenZhinan/img/star.png
ClojurescriptRumenZhinan/js/__init__.py
ClojurescriptRumenZhinan/js/epub.js
ClojurescriptRumenZhinan/js/epub.min.js
ClojurescriptRumenZhinan/js/epub.min.map
ClojurescriptRumenZhinan/js/hooks.min.js
ClojurescriptRumenZhinan/js/hooks.min.map
ClojurescriptRumenZhinan/js/reader.js
ClojurescriptRumenZhinan/js/reader.js.map
ClojurescriptRumenZhinan/js/reader.min.js
ClojurescriptRumenZhinan/js/reader.min.map
ClojurescriptRumenZhinan/js/hooks/__init__.py
ClojurescriptRumenZhinan/js/hooks/extensions/__init__.py
ClojurescriptRumenZhinan/js/hooks/extensions/highlight.js
ClojurescriptRumenZhinan/js/libs/__init__.py
ClojurescriptRumenZhinan/js/libs/jquery.min.js
ClojurescriptRumenZhinan/js/libs/localforage.min.js
ClojurescriptRumenZhinan/js/libs/screenfull.js
clojurescript_rumen_zhinan-2024.3.3.0.dist-info/METADATA
clojurescript_rumen_zhinan-2024.3.3.0.dist-info/WHEEL
clojurescript_rumen_zhinan-2024.3.3.0.dist-info/entry_points.txt
clojurescript_rumen_zhinan-2024.3.3.0.dist-info/top_level.txt
clojurescript_rumen_zhinan-2024.3.3.0.dist-info/RECORD
